bear_tools/__init__.py
bear_tools/dict_utils.py
bear_tools/enhanced_enum.py
bear_tools/enhanced_int_enum.py
bear_tools/example_protocol.yaml
bear_tools/fsm/README.md
bear_tools/fsm/__init__.py
bear_tools/fsm/fsm.py
bear_tools/linting_utils.py
bear_tools/lumberjack/README.md
bear_tools/lumberjack/__init__.py
bear_tools/lumberjack/callback_config.py
bear_tools/lumberjack/color.py
bear_tools/lumberjack/log_level.py
bear_tools/lumberjack/logger.py
bear_tools/macos_utils.py
bear_tools/markdown_utils.py
bear_tools/misc_utils.py
bear_tools/network_utils.py
bear_tools/os_utils.py
bear_tools/publisher/__init__.py
bear_tools/publisher/listener.py
bear_tools/publisher/publisher.py
bear_tools/py.typed
bear_tools/string_utils.py
bear_tools/thread_utils.py
bear_tools/time_utils.py
bear_tools/transport_protocol.py
bear_tools/type_defs.py
bear_tools/yaml_utils.py
bear_tools-0.1.34.dist-info/LICENSE
bear_tools-0.1.34.dist-info/METADATA
bear_tools-0.1.34.dist-info/WHEEL
bear_tools-0.1.34.dist-info/RECORD
