Metadata-Version: 2.3
Name: bear-tools
Version: 0.1.34
Summary: An assortment of QA/Automation related tools
License: MIT
Author: Sean Foley
Author-email: sean.foley.engr@gmail.com
Requires-Python: >=3.10,<4.0
Classifier: License :: OSI Approved :: MIT License
Classifier: Programming Language :: Python :: 3
Classifier: Programming Language :: Python :: 3.10
Classifier: Programming Language :: Python :: 3.11
Classifier: Programming Language :: Python :: 3.12
Classifier: Programming Language :: Python :: 3.13
Requires-Dist: jsonalias (>=0.1.2,<0.2.0)
Requires-Dist: netifaces (>=0.11.0,<0.12.0)
Requires-Dist: pytz (>=2025.2,<2026.0)
Requires-Dist: ruamel-yaml (>=0.18.6,<0.19.0)
Requires-Dist: types-pytz (>=2025.2.0.20250516,<2026.0.0.0)
